[{"x":75508.75,"y":-284250.9375,"z":-14264.39453125,"lat":14.5,"lon":59.4,"id":1281573586480737874,"female":true,"color0":37,"color5":8,"baseLevel":72,"wildLevels":{"health":18,"stamina":9,"oxygen":7,"food":10,"weight":12,"melee":8,"speed":7}},{"x":76338.3671875,"y":-283694.09375,"z":-14247.32421875,"lat":14.5,"lon":59.5,"id":530076200970438985,"female":true,"color0":33,"color5":39,"baseLevel":16,"wildLevels":{"stamina":2,"oxygen":2,"food":4,"weight":4,"speed":3}},{"x":-268535.0,"y":-138415.5625,"z":-14177.5458984375,"lat":32.7,"lon":16.4,"id":2096703919248075522,"color0":22,"color5":39,"baseLevel":28,"wildLevels":{"health":4,"stamina":1,"oxygen":2,"food":9,"weight":3,"melee":3,"speed":5}},{"x":-268564.21875,"y":-138754.3125,"z":-14177.568359375,"lat":32.7,"lon":16.4,"id":1206949959999359965,"color0":39,"color5":38,"baseLevel":52,"wildLevels":{"health":5,"stamina":7,"oxygen":6,"food":6,"weight":4,"melee":14,"speed":9}},{"x":-168134.953125,"y":-204832.109375,"z":23343.69140625,"lat":24.4,"lon":29.0,"id":669518963063611843,"female":true,"color0":21,"color5":39,"baseLevel":20,"wildLevels":{"health":1,"stamina":5,"oxygen":3,"food":4,"weight":2,"melee":1,"speed":3}},{"x":-171406.109375,"y":-131233.078125,"z":-354.888671875,"lat":33.6,"lon":28.6,"id":1450913933706163206,"color0":33,"color5":39,"baseLevel":24,"wildLevels":{"health":3,"stamina":1,"oxygen":1,"food":1,"weight":4,"melee":7,"speed":6}},{"x":-171066.125,"y":-131230.6875,"z":-285.57958984375,"lat":33.6,"lon":28.6,"id":1567157567208665845,"female":true,"color0":37,"color5":39,"baseLevel":44,"wildLevels":{"health":5,"stamina":4,"oxygen":4,"food":5,"weight":10,"melee":9,"speed":6}},{"x":85890.1796875,"y":-236119.5,"z":-10945.837890625,"lat":20.5,"lon":60.7,"id":1833969521238089514,"female":true,"color0":21,"color5":39,"baseLevel":12,"wildLevels":{"health":2,"oxygen":2,"food":1,"weight":2,"melee":3,"speed":1}},{"x":-243399.640625,"y":-198793.421875,"z":3567.25390625,"lat":25.2,"lon":19.6,"id":400118169967249626,"color0":32,"color5":13,"baseLevel":32,"wildLevels":{"health":1,"stamina":8,"oxygen":5,"weight":4,"melee":10,"speed":3}},{"x":-167304.21875,"y":-247879.671875,"z":-5037.4921875,"lat":19.0,"lon":29.1,"id":538784332876352252,"color0":33,"color5":38,"baseLevel":48,"wildLevels":{"health":5,"stamina":7,"oxygen":8,"food":6,"weight":9,"melee":8,"speed":4}},{"x":-80747.484375,"y":-263514.09375,"z":-12792.01953125,"lat":17.1,"lon":39.9,"id":1364469169958093890,"color0":38,"color5":39,"baseLevel":88,"wildLevels":{"health":9,"stamina":14,"oxygen":13,"food":14,"weight":13,"melee":11,"speed":13}},{"x":-80493.8984375,"y":-263287.625,"z":-12795.453125,"lat":17.1,"lon":39.9,"id":1176916443399998945,"female":true,"color0":14,"color5":39,"baseLevel":16,"wildLevels":{"health":2,"stamina":4,"oxygen":1,"food":1,"weight":3,"speed":4}},{"x":-36677.12109375,"y":-160627.5,"z":470.58819580078125,"lat":29.9,"lon":45.4,"id":976678707330957356,"color0":37,"color5":39,"baseLevel":12,"wildLevels":{"health":1,"oxygen":1,"food":4,"weight":1,"melee":2,"speed":2}},{"x":-35727.1875,"y":-159626.828125,"z":719.3631591796875,"lat":30.0,"lon":45.5,"id":1941583826754003333,"color0":39,"color5":35,"baseLevel":76,"wildLevels":{"health":12,"stamina":10,"oxygen":10,"food":12,"weight":9,"melee":11,"speed":11}},{"x":-13472.7548828125,"y":-203374.9375,"z":5105.7373046875,"lat":24.6,"lon":48.3,"id":1971372938011699079,"color0":34,"color5":35,"baseLevel":16,"wildLevels":{"health":2,"stamina":4,"food":3,"weight":3,"melee":2,"speed":1}},{"x":29844.15234375,"y":-143369.328125,"z":1145.2879638671875,"lat":32.1,"lon":53.7,"id":1057757540723628463,"female":true,"color0":37,"color5":39,"baseLevel":8,"wildLevels":{"food":4,"melee":1,"speed":2}},{"x":31511.025390625,"y":-142661.625,"z":1344.8406982421875,"lat":32.2,"lon":53.9,"id":647297201679695452,"female":true,"color0":21,"color5":8,"baseLevel":76,"wildLevels":{"health":8,"stamina":15,"oxygen":12,"food":14,"weight":11,"melee":6,"speed":9}},{"x":5922.00927734375,"y":-145931.40625,"z":-3.009765625,"lat":31.8,"lon":50.7,"id":1290694997567060670,"female":true,"color0":38,"color5":39,"baseLevel":36,"wildLevels":{"health":4,"stamina":2,"oxygen":6,"food":6,"weight":8,"melee":4,"speed":5}},{"x":-257307.890625,"y":-201051.828125,"z":-3489.73046875,"lat":24.9,"lon":17.8,"id":303165957612351799,"color0":37,"color5":39,"baseLevel":88,"wildLevels":{"health":13,"stamina":11,"oxygen":15,"food":12,"weight":12,"melee":11,"speed":13}},{"x":-70978.3203125,"y":-185469.265625,"z":-3785.944580078125,"lat":26.8,"lon":41.1,"id":1430526002958950304,"color0":33,"color5":38,"baseLevel":28,"wildLevels":{"health":4,"stamina":3,"oxygen":3,"food":3,"weight":3,"melee":7,"speed":4}},{"x":68622.7421875,"y":-197428.78125,"z":1729.138671875,"lat":25.3,"lon":58.6,"id":1051207857342876105,"female":true,"color0":37,"color5":38,"baseLevel":24,"wildLevels":{"health":6,"stamina":5,"oxygen":1,"food":2,"weight":4,"melee":2,"speed":3}},{"x":9312.6962890625,"y":-295298.46875,"z":-13177.2158203125,"lat":13.1,"lon":51.2,"id":1868029316049484037,"color0":33,"color5":21,"baseLevel":8,"wildLevels":{"health":1,"stamina":4,"food":1,"speed":1}},{"x":-198216.25,"y":-234132.03125,"z":8634.8359375,"lat":20.7,"lon":25.2,"id":1583216488646826493,"color0":32,"color5":33,"baseLevel":68,"wildLevels":{"health":5,"stamina":14,"oxygen":6,"food":10,"weight":9,"melee":13,"speed":10}},{"x":-197892.984375,"y":-234237.40625,"z":8658.8798828125,"lat":20.7,"lon":25.3,"id":967691664212941327,"color0":34,"color5":39,"baseLevel":4,"wildLevels":{"health":1,"food":1,"weight":1}},{"x":-113004.2734375,"y":123484.1953125,"z":-10455.904296875,"lat":65.4,"lon":35.9,"id":164045708950583065,"female":true,"color0":35,"color5":35,"baseLevel":56,"wildLevels":{"health":5,"stamina":5,"oxygen":4,"food":10,"weight":8,"melee":12,"speed":11}},{"x":-113001.9296875,"y":123824.1875,"z":-10403.712890625,"lat":65.5,"lon":35.9,"id":764986920616984908,"female":true,"color0":38,"color5":39,"baseLevel":16,"wildLevels":{"health":1,"stamina":1,"food":1,"weight":4,"melee":3,"speed":5}},{"x":-8070.953125,"y":-276976.09375,"z":-5239.3369140625,"lat":15.4,"lon":49.0,"id":1415090702281064324,"color0":8,"color5":32,"baseLevel":8,"wildLevels":{"health":1,"food":1,"melee":2,"speed":3}},{"x":61679.703125,"y":-154500.09375,"z":4912.458984375,"lat":30.7,"lon":57.7,"id":400928033253204203,"color0":35,"color5":39,"baseLevel":8,"wildLevels":{"stamina":1,"oxygen":2,"food":1,"weight":1,"melee":1,"speed":1}},{"x":63141.62890625,"y":-153983.28125,"z":4993.24755859375,"lat":30.8,"lon":57.9,"id":211383687878224446,"female":true,"color0":14,"color5":13,"baseLevel":12,"wildLevels":{"health":2,"stamina":1,"oxygen":2,"food":2,"weight":4}},{"x":-38206.53125,"y":-253676.8125,"z":-9048.44140625,"lat":18.3,"lon":45.2,"id":2121577474972821167,"color0":33,"color5":39,"baseLevel":44,"wildLevels":{"health":7,"stamina":9,"oxygen":5,"food":7,"weight":4,"melee":6,"speed":5}},{"x":-298030.03125,"y":-191051.46875,"z":-7894.16796875,"lat":26.1,"lon":12.7,"id":73082584080814550,"female":true,"color0":14,"color5":37,"baseLevel":28,"wildLevels":{"health":5,"stamina":3,"oxygen":5,"food":2,"weight":2,"melee":1,"speed":9}},{"x":-247062.375,"y":-124360.453125,"z":-12320.166015625,"lat":34.5,"lon":19.1,"id":604563707085954118,"color0":13,"color5":21,"baseLevel":20,"wildLevels":{"health":3,"stamina":1,"oxygen":1,"food":2,"weight":6,"melee":3,"speed":3}},{"x":-246752.34375,"y":-124500.03125,"z":-12092.609375,"lat":34.4,"lon":19.2,"id":819813453715862788,"female":true,"color0":33,"color5":33,"baseLevel":12,"wildLevels":{"health":1,"stamina":3,"food":1,"weight":1,"speed":5}},{"x":-4304.82568359375,"y":-162128.46875,"z":2297.970703125,"lat":29.7,"lon":49.5,"id":521454642426657660,"female":true,"color0":37,"color5":39,"baseLevel":20,"wildLevels":{"health":3,"stamina":3,"oxygen":3,"food":1,"weight":3,"melee":5,"speed":1}},{"x":41140.59765625,"y":-274452.21875,"z":-3888.640869140625,"lat":15.7,"lon":55.1,"id":1391888249642866606,"color0":14,"color5":39,"baseLevel":16,"wildLevels":{"health":1,"stamina":7,"oxygen":4,"weight":1,"speed":2}},{"x":-283993.5,"y":-230417.984375,"z":-5675.5078125,"lat":21.2,"lon":14.5,"id":682008096592648783,"female":true,"color0":39,"color5":14,"baseLevel":52,"wildLevels":{"health":8,"stamina":12,"oxygen":5,"food":6,"weight":7,"melee":2,"speed":11}},{"x":-226381.03125,"y":-233214.28125,"z":-1249.11279296875,"lat":20.8,"lon":21.7,"id":525403963778991135,"female":true,"color0":8,"color5":39,"baseLevel":4,"wildLevels":{"stamina":2,"food":1}},{"x":-116917.765625,"y":-168021.953125,"z":714.37109375,"lat":29.0,"lon":35.4,"id":1215646289806069232,"female":true,"color0":34,"color5":37,"baseLevel":12,"wildLevels":{"health":3,"stamina":1,"food":2,"weight":4,"melee":1}},{"x":-187880.09375,"y":-143140.703125,"z":-1264.23046875,"lat":32.1,"lon":26.5,"id":365840465665037312,"color0":22,"color5":33,"baseLevel":8,"wildLevels":{"oxygen":1,"food":1,"weight":2,"melee":1,"speed":2}},{"x":-188211.421875,"y":-143217.0,"z":-1218.203125,"lat":32.1,"lon":26.5,"id":1778636323515481515,"color0":37,"color5":39,"baseLevel":12,"wildLevels":{"health":3,"stamina":3,"oxygen":1,"weight":3,"speed":1}},{"x":-114296.53125,"y":-204812.953125,"z":8000.853515625,"lat":24.4,"lon":35.7,"id":881691773048764968,"color0":39,"color5":38,"baseLevel":12,"wildLevels":{"health":1,"stamina":1,"oxygen":1,"food":2,"weight":1,"melee":2,"speed":3}},{"x":-114056.6640625,"y":-204571.984375,"z":8026.462890625,"lat":24.4,"lon":35.7,"id":557690719033145967,"color0":34,"color5":35,"baseLevel":12,"wildLevels":{"stamina":1,"oxygen":1,"food":5,"weight":2,"melee":1,"speed":1}},{"x":-34413.9765625,"y":99121.8984375,"z":-5200.7041015625,"lat":62.4,"lon":45.7,"id":1887523709111069483,"color0":33,"color5":39,"baseLevel":12,"wildLevels":{"health":1,"oxygen":1,"food":4,"weight":2,"melee":1,"speed":2}},{"x":-34695.828125,"y":98931.7421875,"z":-5121.46240234375,"lat":62.4,"lon":45.7,"id":2006399861089279014,"female":true,"color0":34,"color5":13,"baseLevel":88,"wildLevels":{"health":8,"stamina":9,"oxygen":13,"food":11,"weight":17,"melee":15,"speed":14}},{"x":83530.6953125,"y":-200762.953125,"z":-535.49609375,"lat":24.9,"lon":60.4,"id":1522423335298949614,"color0":14,"color5":39,"baseLevel":8,"wildLevels":{"health":1,"oxygen":1,"weight":1,"melee":2,"speed":2}},{"x":83672.4609375,"y":-200453.921875,"z":-591.1484375,"lat":24.9,"lon":60.5,"id":2125552853597274443,"color0":38,"color5":39,"baseLevel":16,"wildLevels":{"health":3,"stamina":2,"oxygen":2,"food":4,"weight":2,"melee":1,"speed":1}}]